zenodo_get/__init__.py
zenodo_get/__main__.py
zenodo_get/downloader.py
zenodo_get/zget.py
zenodo_get-3.0.0.dist-info/WHEEL
zenodo_get-3.0.0.dist-info/entry_points.txt
zenodo_get-3.0.0.dist-info/METADATA
zenodo_get-3.0.0.dist-info/RECORD
