Metadata-Version: 2.3
Name: zenodo-get
Version: 3.0.0
Summary: Zenodo_get - a downloader for Zenodo records
Keywords: zenodo,download
Author: David Völgyes
Author-email: David Völgyes <david.volgyes@ieee.org>
License:                     GNU AFFERO GENERAL PUBLIC LICENSE
Classifier: Development Status :: 4 - Beta
Classifier: Operating System :: OS Independent
Classifier: Programming Language :: Python
Classifier: Programming Language :: Python :: 3
Classifier: Programming Language :: Python :: 3.10
Classifier: Programming Language :: Python :: 3.11
Classifier: Programming Language :: Python :: 3.12
Classifier: Programming Language :: Python :: 3.13
Classifier: Programming Language :: Python :: 3.14
Classifier: Intended Audience :: Science/Research
Classifier: License :: OSI Approved :: GNU Affero General Public License v3
Requires-Dist: httpx
Requires-Dist: humanize
Requires-Dist: click
Requires-Dist: loguru
Requires-Dist: tqdm
Requires-Dist: coverage>=7.8.2
Requires-Dist: httpx-retries>=0.4.5
Requires-Dist: coverage ; extra == 'dev'
Requires-Dist: codecov ; extra == 'dev'
Requires-Dist: coveralls ; extra == 'dev'
Requires-Python: >=3.10
Project-URL: Homepage, https://github.com/dvolgyes/zenodo_get
Provides-Extra: dev
